django_template_preview-0.1.5.dist-info/DESCRIPTION.rst
django_template_preview-0.1.5.dist-info/METADATA
django_template_preview-0.1.5.dist-info/RECORD
django_template_preview-0.1.5.dist-info/WHEEL
django_template_preview-0.1.5.dist-info/metadata.json
django_template_preview-0.1.5.dist-info/top_level.txt
template_preview/__init__.py
template_preview/constants.py
template_preview/forms.py
template_preview/urls.py
template_preview/views.py
template_preview/static/._css
template_preview/static/._js
template_preview/static/css/._app.css
template_preview/static/css/._foundation.css
template_preview/static/css/._foundation.min.css
template_preview/static/css/app.css
template_preview/static/css/foundation.css
template_preview/static/css/foundation.min.css
template_preview/static/js/._app.js
template_preview/static/js/._vendor
template_preview/static/js/app.js
template_preview/static/js/vendor/._foundation.js
template_preview/static/js/vendor/._foundation.min.js
template_preview/static/js/vendor/._jquery.js
template_preview/static/js/vendor/._what-input.js
template_preview/static/js/vendor/foundation.js
template_preview/static/js/vendor/foundation.min.js
template_preview/static/js/vendor/jquery.js
template_preview/static/js/vendor/what-input.js
template_preview/templates/._preview_base.html
template_preview/templates/edit_detail.html
template_preview/templates/list.html
template_preview/templates/preview_base.html
